algo_lib/__init__.py
algo_lib/math/__init__.py
algo_lib/math/fibonacci.py
algo_lib/math/prime.py
algo_lib/ml/__init__.py
algo_lib/ml/linear_regression.py
algo_lib/sampling/__init__.py
algo_lib/sampling/reservoir_sample.py
algo_lib/simulation/simulate_people.py
algo_library-0.0.10.dist-info/LICENSE
algo_library-0.0.10.dist-info/METADATA
algo_library-0.0.10.dist-info/WHEEL
algo_library-0.0.10.dist-info/RECORD
